{"type": "FeatureCollection", "features": [{"type": "Feature", "geometry": {"type": "Point", "coordinates": [-79.35249328613281, 43.70155715942383]}, "properties": {"stop_id": "2927", "stop_name": "Millwood Rd at Overlea Blvd South Side"}}, {"type": "Feature", "geometry": {"type": "Point", "coordinates": [-79.34880828857422, 43.69697189331055]}, "properties": {"stop_id": "9448", "stop_name": "Donlands Ave at Pape Ave East Side"}}, {"type": "Feature", "geometry": {"type": "Point", "coordinates": [-79.37742614746094, 43.71088409423828]}, "properties": {"stop_id": "2238", "stop_name": "Eglinton Ave East at Bayview Ave"}}, {"type": "Feature", "geometry": {"type": "Point", "coordinates": [-79.33880615234375, 43.683837890625]}, "properties": {"stop_id": "16479", "stop_name": "Donlands Ave at Milverton Blvd"}}, {"type": "Feature", "geometry": {"type": "Point", "coordinates": [-79.34098052978516, 43.68914794921875]}, "properties": {"stop_id": "962", "stop_name": "Donlands Ave at Floyd Ave"}}, {"type": "Feature", "geometry": {"type": "Point", "coordinates": [-79.36076354980469, 43.70330810546875]}, "properties": {"stop_id": "15671", "stop_name": "Laird Dr at Millwood Rd"}}, {"type": "Feature", "geometry": {"type": "Point", "coordinates": [-79.3956069946289, 43.70720672607422]}, "properties": {"stop_id": "15702", "stop_name": "Eglinton Ave East at Dunfield Ave"}}, {"type": "Feature", "geometry": {"type": "Point", "coordinates": [-79.3619384765625, 43.70623016357422]}, "properties": {"stop_id": "5143", "stop_name": "Laird Dr at Lea Ave"}}, {"type": "Feature", "geometry": {"type": "Point", "coordinates": [-79.34471893310547, 43.695796966552734]}, "properties": {"stop_id": "9449", "stop_name": "Donlands Ave at Elmsdale Rd"}}, {"type": "Feature", "geometry": {"type": "Point", "coordinates": [-79.36975860595703, 43.71245574951172]}, "properties": {"stop_id": "2308", "stop_name": "Eglinton Ave East at Rumsey Rd"}}, {"type": "Feature", "geometry": {"type": "Point", "coordinates": [-79.36128997802734, 43.70460891723633]}, "properties": {"stop_id": "5142", "stop_name": "Laird Dr at Kenrae Rd"}}, {"type": "Feature", "geometry": {"type": "Point", "coordinates": [-79.39849853515625, 43.70476150512695]}, "properties": {"stop_id": "14670", "stop_name": "Eglinton Station"}}, {"type": "Feature", "geometry": {"type": "Point", "coordinates": [-79.34159088134766, 43.690677642822266]}, "properties": {"stop_id": "960", "stop_name": "Donlands Ave at Cosburn Ave South Side"}}, {"type": "Feature", "geometry": {"type": "Point", "coordinates": [-79.38233947753906, 43.70991516113281]}, "properties": {"stop_id": "2234", "stop_name": "Eglinton Ave East at Banff Rd"}}, {"type": "Feature", "geometry": {"type": "Point", "coordinates": [-79.36500549316406, 43.713436126708984]}, "properties": {"stop_id": "5071", "stop_name": "Eglinton Ave East at Laird Dr"}}, {"type": "Feature", "geometry": {"type": "Point", "coordinates": [-79.357666015625, 43.701744079589844]}, "properties": {"stop_id": "5752", "stop_name": "Millwood Rd at Redway Rd South Side"}}, {"type": "Feature", "geometry": {"type": "Point", "coordinates": [-79.34038543701172, 43.68770217895508]}, "properties": {"stop_id": "966", "stop_name": "Donlands Ave at Mortimer Ave"}}, {"type": "Feature", "geometry": {"type": "Point", "coordinates": [-79.3377914428711, 43.68084716796875]}, "properties": {"stop_id": "14649", "stop_name": "Donlands Station"}}, {"type": "Feature", "geometry": {"type": "Point", "coordinates": [-79.3430404663086, 43.694244384765625]}, "properties": {"stop_id": "967", "stop_name": "Donlands Ave at O'Connor Dr South Side"}}, {"type": "Feature", "geometry": {"type": "Point", "coordinates": [-79.34245300292969, 43.692848205566406]}, "properties": {"stop_id": "976", "stop_name": "Donlands Ave at Torrens Ave"}}, {"type": "Feature", "geometry": {"type": "Point", "coordinates": [-79.3628158569336, 43.70829391479492]}, "properties": {"stop_id": "15870", "stop_name": "Laird Dr at Commercial Rd South Side"}}, {"type": "Feature", "geometry": {"type": "Point", "coordinates": [-79.39042663574219, 43.708282470703125]}, "properties": {"stop_id": "16332", "stop_name": "Eglinton Ave East at Mount Pleasant Rd"}}, {"type": "Feature", "geometry": {"type": "Point", "coordinates": [-79.36732482910156, 43.71296310424805]}, "properties": {"stop_id": "2312", "stop_name": "Eglinton Ave East at Sutherland Dr"}}, {"type": "Feature", "geometry": {"type": "Point", "coordinates": [-79.33966827392578, 43.68592834472656]}, "properties": {"stop_id": "971", "stop_name": "Donlands Ave at Sammon Ave"}}, {"type": "Feature", "geometry": {"type": "Point", "coordinates": [-79.3636703491211, 43.71052551269531]}, "properties": {"stop_id": "5145", "stop_name": "Laird Dr at McRae Dr"}}, {"type": "Feature", "geometry": {"type": "Point", "coordinates": [-79.39293670654297, 43.70775604248047]}, "properties": {"stop_id": "2304", "stop_name": "Eglinton Ave East at Redpath Ave"}}, {"type": "Feature", "geometry": {"type": "Point", "coordinates": [-79.40010833740234, 43.70623016357422]}, "properties": {"stop_id": "13898", "stop_name": "Duplex Ave at Eglinton Ave West"}}, {"type": "Feature", "geometry": {"type": "Point", "coordinates": [-79.3863296508789, 43.7091064453125]}, "properties": {"stop_id": "2270", "stop_name": "Eglinton Ave East at Forman Ave"}}, {"type": "Feature", "geometry": {"type": "Point", "coordinates": [-79.37360382080078, 43.711708068847656]}, "properties": {"stop_id": "16123", "stop_name": "Eglinton Ave East at Donlea Dr"}}]}