{"type": "FeatureCollection", "features": [{"type": "Feature", "geometry": {"type": "Point", "coordinates": [-79.34742736816406, 43.75556945800781]}, "properties": {"stop_id": "9070", "stop_name": "York Mills Rd at Don Mills Rd"}}, {"type": "Feature", "geometry": {"type": "Point", "coordinates": [-79.61959838867188, 43.730594635009766]}, "properties": {"stop_id": "12200", "stop_name": "Humberwood Blvd at Topbank Dr North Side"}}, {"type": "Feature", "geometry": {"type": "Point", "coordinates": [-79.62122344970703, 43.72447204589844]}, "properties": {"stop_id": "11289", "stop_name": "Humberwood Blvd Loop at View Green Cres"}}, {"type": "Feature", "geometry": {"type": "Point", "coordinates": [-79.55086517333984, 43.72491455078125]}, "properties": {"stop_id": "7724", "stop_name": "Elmhurst Dr at Albion Rd"}}, {"type": "Feature", "geometry": {"type": "Point", "coordinates": [-79.61734008789062, 43.732200622558594]}, "properties": {"stop_id": "13472", "stop_name": "Humberline Dr at Viewcrest Cir East Side"}}, {"type": "Feature", "geometry": {"type": "Point", "coordinates": [-79.62205505371094, 43.72604751586914]}, "properties": {"stop_id": "14513", "stop_name": "Humberwood Blvd at Morning Star Dr"}}, {"type": "Feature", "geometry": {"type": "Point", "coordinates": [-79.36022186279297, 43.75278854370117]}, "properties": {"stop_id": "9076", "stop_name": "York Mills Rd at Leslie St"}}, {"type": "Feature", "geometry": {"type": "Point", "coordinates": [-79.48238372802734, 43.72642517089844]}, "properties": {"stop_id": "8868", "stop_name": "Wilson Ave at Keele St"}}, {"type": "Feature", "geometry": {"type": "Point", "coordinates": [-79.58615112304688, 43.7260627746582]}, "properties": {"stop_id": "8657", "stop_name": "Westhumber Blvd at Martin Grove Rd East Side"}}, {"type": "Feature", "geometry": {"type": "Point", "coordinates": [-79.31044006347656, 43.758846282958984]}, "properties": {"stop_id": "6368", "stop_name": "Ellesmere Rd at Pharmacy Ave"}}, {"type": "Feature", "geometry": {"type": "Point", "coordinates": [-79.25840759277344, 43.774208068847656]}, "properties": {"stop_id": "14759", "stop_name": "Scarborough Centre Station"}}, {"type": "Feature", "geometry": {"type": "Point", "coordinates": [-79.61217498779297, 43.73173522949219]}, "properties": {"stop_id": "11048", "stop_name": "Humberline Dr at Holyoake Cres (East)"}}, {"type": "Feature", "geometry": {"type": "Point", "coordinates": [-79.30106353759766, 43.76095962524414]}, "properties": {"stop_id": "7719", "stop_name": "Ellesmere Rd at Warden Ave"}}, {"type": "Feature", "geometry": {"type": "Point", "coordinates": [-79.59953308105469, 43.730804443359375]}, "properties": {"stop_id": "15821", "stop_name": "Humber College Blvd at Westmore Dr - Etobicoke General Hospital"}}, {"type": "Feature", "geometry": {"type": "Point", "coordinates": [-79.45110321044922, 43.73491668701172]}, "properties": {"stop_id": "14820", "stop_name": "Wilson Station"}}, {"type": "Feature", "geometry": {"type": "Point", "coordinates": [-79.61990356445312, 43.729042053222656]}, "properties": {"stop_id": "11851", "stop_name": "Humberwood Blvd at Pinecone Dr North Side"}}, {"type": "Feature", "geometry": {"type": "Point", "coordinates": [-79.384521484375, 43.74787139892578]}, "properties": {"stop_id": "9188", "stop_name": "York Mills Rd at Bayview Ave"}}, {"type": "Feature", "geometry": {"type": "Point", "coordinates": [-79.28144836425781, 43.76559066772461]}, "properties": {"stop_id": "7693", "stop_name": "Ellesmere Rd at Kennedy Rd"}}, {"type": "Feature", "geometry": {"type": "Point", "coordinates": [-79.49069213867188, 43.72458267211914]}, "properties": {"stop_id": "8865", "stop_name": "Wilson Ave at Julian Rd East Side - Humber River Hospital"}}, {"type": "Feature", "geometry": {"type": "Point", "coordinates": [-79.32373809814453, 43.760929107666016]}, "properties": {"stop_id": "8025", "stop_name": "Parkwoods Village Dr at Brookbanks Dr"}}, {"type": "Feature", "geometry": {"type": "Point", "coordinates": [-79.5590591430664, 43.72298812866211]}, "properties": {"stop_id": "7731", "stop_name": "Elmhurst Dr at Islington Ave"}}, {"type": "Feature", "geometry": {"type": "Point", "coordinates": [-79.26142883300781, 43.77348327636719]}, "properties": {"stop_id": "1613", "stop_name": "Triton Rd at Borough Dr"}}, {"type": "Feature", "geometry": {"type": "Point", "coordinates": [-79.60184478759766, 43.73024368286133]}, "properties": {"stop_id": "11273", "stop_name": "Humber College Blvd at Highway 27"}}, {"type": "Feature", "geometry": {"type": "Point", "coordinates": [-79.40582275390625, 43.74521255493164]}, "properties": {"stop_id": "14814", "stop_name": "York Mills Station"}}, {"type": "Feature", "geometry": {"type": "Point", "coordinates": [-79.60956573486328, 43.73186111450195]}, "properties": {"stop_id": "11049", "stop_name": "Humberline Dr at Humber College Blvd"}}, {"type": "Feature", "geometry": {"type": "Point", "coordinates": [-79.61502838134766, 43.731956481933594]}, "properties": {"stop_id": "11047", "stop_name": "Humberline Dr at Woodlot Cres (West) East Side"}}, {"type": "Feature", "geometry": {"type": "Point", "coordinates": [-79.33279418945312, 43.759403228759766]}, "properties": {"stop_id": "16688", "stop_name": "York Mills Rd at Valley Woods Rd"}}, {"type": "Feature", "geometry": {"type": "Point", "coordinates": [-79.5088119506836, 43.72075271606445]}, "properties": {"stop_id": "8861", "stop_name": "Wilson Ave at Jane St"}}, {"type": "Feature", "geometry": {"type": "Point", "coordinates": [-79.45951843261719, 43.73185348510742]}, "properties": {"stop_id": "1657", "stop_name": "Wilson Ave at Dufferin St"}}, {"type": "Feature", "geometry": {"type": "Point", "coordinates": [-79.57478332519531, 43.72798538208008]}, "properties": {"stop_id": "8656", "stop_name": "Westhumber Blvd at Kipling Ave"}}, {"type": "Feature", "geometry": {"type": "Point", "coordinates": [-79.53826904296875, 43.717247009277344]}, "properties": {"stop_id": "7481", "stop_name": "Albion Rd at Weston Rd"}}, {"type": "Feature", "geometry": {"type": "Point", "coordinates": [-79.31460571289062, 43.757877349853516]}, "properties": {"stop_id": "6371", "stop_name": "Ellesmere Rd at Victoria Park Ave East Side"}}, {"type": "Feature", "geometry": {"type": "Point", "coordinates": [-79.61851501464844, 43.733428955078125]}, "properties": {"stop_id": "11508", "stop_name": "Humberwood Blvd at Humberline Dr"}}, {"type": "Feature", "geometry": {"type": "Point", "coordinates": [-79.47785949707031, 43.72804260253906]}, "properties": {"stop_id": "8848", "stop_name": "Wilson Ave at Dubray Ave"}}, {"type": "Feature", "geometry": {"type": "Point", "coordinates": [-79.58960723876953, 43.73189926147461]}, "properties": {"stop_id": "7876", "stop_name": "John Garland Blvd at Martin Grove Rd"}}, {"type": "Feature", "geometry": {"type": "Point", "coordinates": [-79.53679656982422, 43.71673583984375]}, "properties": {"stop_id": "8525", "stop_name": "Walsh Ave at Weston Rd East Side"}}, {"type": "Feature", "geometry": {"type": "Point", "coordinates": [-79.27146911621094, 43.76771926879883]}, "properties": {"stop_id": "7696", "stop_name": "Ellesmere Rd at Midland Ave"}}, {"type": "Feature", "geometry": {"type": "Point", "coordinates": [-79.29161834716797, 43.763214111328125]}, "properties": {"stop_id": "7678", "stop_name": "Ellesmere Rd at Birchmount Rd"}}, {"type": "Feature", "geometry": {"type": "Point", "coordinates": [-79.37054443359375, 43.75133514404297]}, "properties": {"stop_id": "7467", "stop_name": "York Mills Rd at Chipstead Rd"}}, {"type": "Feature", "geometry": {"type": "Point", "coordinates": [-79.42190551757812, 43.73970031738281]}, "properties": {"stop_id": "8837", "stop_name": "Wilson Ave at Avenue Rd"}}, {"type": "Feature", "geometry": {"type": "Point", "coordinates": [-79.5235366821289, 43.71747589111328]}, "properties": {"stop_id": "8845", "stop_name": "Wilson Ave at Clayson Rd"}}, {"type": "Feature", "geometry": {"type": "Point", "coordinates": [-79.60453033447266, 43.728965759277344]}, "properties": {"stop_id": "15403", "stop_name": "Humber College Bus Terminal"}}, {"type": "Feature", "geometry": {"type": "Point", "coordinates": [-79.4332275390625, 43.7373046875]}, "properties": {"stop_id": "8839", "stop_name": "Wilson Ave at Bathurst St East Side"}}, {"type": "Feature", "geometry": {"type": "Point", "coordinates": [-79.54597473144531, 43.721309661865234]}, "properties": {"stop_id": "6216", "stop_name": "Albion Rd at Armel Crt"}}]}