{"type": "FeatureCollection", "features": [{"type": "Feature", "geometry": {"type": "Point", "coordinates": [-79.41764831542969, 43.78788375854492]}, "properties": {"vehicle_id": "3460", "trip_id": "82316020", "direction_id": null, "bearing": 178.0, "arrow_bearing": 268.0, "speed": 4.917439937591553, "label": ""}}, {"type": "Feature", "geometry": {"type": "Point", "coordinates": [-79.39897918701172, 43.709129333496094]}, "properties": {"vehicle_id": "7021", "trip_id": "15940020", "direction_id": null, "bearing": 169.0, "arrow_bearing": 259.0, "speed": 0.0, "label": ""}}, {"type": "Feature", "geometry": {"type": "Point", "coordinates": [-79.38597106933594, 43.66830825805664]}, "properties": {"vehicle_id": "7047", "trip_id": "51413020", "direction_id": null, "bearing": 344.0, "arrow_bearing": 74.0, "speed": 0.0, "label": ""}}, {"type": "Feature", "geometry": {"type": "Point", "coordinates": [-79.39847564697266, 43.7043571472168]}, "properties": {"vehicle_id": "7061", "trip_id": "95450020", "direction_id": null, "bearing": 330.0, "arrow_bearing": 60.0, "speed": 0.0, "label": ""}}, {"type": "Feature", "geometry": {"type": "Point", "coordinates": [-79.40499114990234, 43.73436737060547]}, "properties": {"vehicle_id": "3519", "trip_id": "17805020", "direction_id": null, "bearing": 259.0, "arrow_bearing": 349.0, "speed": 4.023359775543213, "label": ""}}, {"type": "Feature", "geometry": {"type": "Point", "coordinates": [-79.3786392211914, 43.64619445800781]}, "properties": {"vehicle_id": "3524", "trip_id": "31340020", "direction_id": null, "bearing": 259.0, "arrow_bearing": 349.0, "speed": 0.0, "label": ""}}, {"type": "Feature", "geometry": {"type": "Point", "coordinates": [-79.39805603027344, 43.70489501953125]}, "properties": {"vehicle_id": "3534", "trip_id": "6683020", "direction_id": null, "bearing": 172.0, "arrow_bearing": 262.0, "speed": 6.705599784851074, "label": ""}}]}