[{"route_id":1,"route_long_name":"Line 1 (Yonge-University)"},{"route_id":2,"route_long_name":"Line 2 (Bloor - Danforth)"},{"route_id":4,"route_long_name":"Line 4 (Sheppard)"},{"route_id":6,"route_long_name":"Finch West"},{"route_id":7,"route_long_name":"Bathurst"},{"route_id":8,"route_long_name":"Broadview"},{"route_id":9,"route_long_name":"Bellamy"},{"route_id":10,"route_long_name":"Van Horne"},{"route_id":11,"route_long_name":"Bayview"},{"route_id":12,"route_long_name":"Kingston Rd"},{"route_id":13,"route_long_name":"Avenue Rd"},{"route_id":14,"route_long_name":"Glencairn"},{"route_id":15,"route_long_name":"Evans"},{"route_id":16,"route_long_name":"McCowan"},{"route_id":17,"route_long_name":"Birchmount"},{"route_id":19,"route_long_name":"Bay"},{"route_id":20,"route_long_name":"Cliffside"},{"route_id":21,"route_long_name":"Brimley"},{"route_id":22,"route_long_name":"Coxwell"},{"route_id":23,"route_long_name":"Dawes"},{"route_id":24,"route_long_name":"Victoria Park"},{"route_id":25,"route_long_name":"Don Mills"},{"route_id":26,"route_long_name":"Dupont"},{"route_id":28,"route_long_name":"Bayview South"},{"route_id":29,"route_long_name":"Dufferin"},{"route_id":30,"route_long_name":"High Park North"},{"route_id":31,"route_long_name":"Greenwood"},{"route_id":32,"route_long_name":"Eglinton West"},{"route_id":33,"route_long_name":"Forest Hill"},{"route_id":34,"route_long_name":"Eglinton East"},{"route_id":35,"route_long_name":"Jane"},{"route_id":36,"route_long_name":"Finch West"},{"route_id":37,"route_long_name":"Islington"},{"route_id":38,"route_long_name":"Highland Creek"},{"route_id":39,"route_long_name":"Finch East"},{"route_id":40,"route_long_name":"Junction-Dundas West"},{"route_id":41,"route_long_name":"Keele"},{"route_id":42,"route_long_name":"Cummer"},{"route_id":43,"route_long_name":"Kennedy"},{"route_id":44,"route_long_name":"Kipling South"},{"route_id":45,"route_long_name":"Kipling"},{"route_id":46,"route_long_name":"Martin Grove"},{"route_id":47,"route_long_name":"Lansdowne"},{"route_id":48,"route_long_name":"Rathburn"},{"route_id":49,"route_long_name":"Bloor West"},{"route_id":50,"route_long_name":"Burnhamthorpe"},{"route_id":51,"route_long_name":"Leslie"},{"route_id":52,"route_long_name":"Lawrence West"},{"route_id":53,"route_long_name":"Steeles East"},{"route_id":54,"route_long_name":"Lawrence East"},{"route_id":55,"route_long_name":"Warren Park"},{"route_id":56,"route_long_name":"Leaside"},{"route_id":57,"route_long_name":"Midland"},{"route_id":59,"route_long_name":"Maple Leaf"},{"route_id":60,"route_long_name":"Steeles West"},{"route_id":61,"route_long_name":"Avenue Rd North"},{"route_id":62,"route_long_name":"Mortimer"},{"route_id":63,"route_long_name":"Ossington"},{"route_id":64,"route_long_name":"Main"},{"route_id":65,"route_long_name":"Parliament"},{"route_id":66,"route_long_name":"Prince Edward"},{"route_id":67,"route_long_name":"Pharmacy"},{"route_id":68,"route_long_name":"Warden"},{"route_id":69,"route_long_name":"Warden South"},{"route_id":70,"route_long_name":"O'Connor"},{"route_id":71,"route_long_name":"Runnymede"},{"route_id":72,"route_long_name":"Pape"},{"route_id":73,"route_long_name":"Royal York"},{"route_id":74,"route_long_name":"Mount Pleasant"},{"route_id":75,"route_long_name":"Sherbourne"},{"route_id":76,"route_long_name":"Royal York South"},{"route_id":77,"route_long_name":"Swansea"},{"route_id":78,"route_long_name":"St Andrews"},{"route_id":79,"route_long_name":"Scarlett Rd"},{"route_id":80,"route_long_name":"Queensway"},{"route_id":82,"route_long_name":"Rosedale"},{"route_id":83,"route_long_name":"Jones"},{"route_id":84,"route_long_name":"Sheppard West"},{"route_id":85,"route_long_name":"Sheppard East"},{"route_id":86,"route_long_name":"Scarborough"},{"route_id":87,"route_long_name":"Cosburn"},{"route_id":88,"route_long_name":"South Leaside"},{"route_id":89,"route_long_name":"Weston"},{"route_id":90,"route_long_name":"Vaughan"},{"route_id":91,"route_long_name":"Woodbine"},{"route_id":92,"route_long_name":"Woodbine South"},{"route_id":93,"route_long_name":"Parkview Hills"},{"route_id":94,"route_long_name":"Wellesley"},{"route_id":95,"route_long_name":"York Mills"},{"route_id":96,"route_long_name":"Wilson"},{"route_id":97,"route_long_name":"Yonge"},{"route_id":98,"route_long_name":"Willowdale-Senlac"},{"route_id":99,"route_long_name":"Arrow Rd"},{"route_id":100,"route_long_name":"Flemingdon Park"},{"route_id":101,"route_long_name":"Downsview Park"},{"route_id":102,"route_long_name":"Markham Rd"},{"route_id":103,"route_long_name":"Mount Pleasant North"},{"route_id":104,"route_long_name":"Faywood"},{"route_id":105,"route_long_name":"Dufferin North"},{"route_id":106,"route_long_name":"Sentinel"},{"route_id":107,"route_long_name":"Alness-Chesswood"},{"route_id":108,"route_long_name":"Driftwood"},{"route_id":109,"route_long_name":"Ranee"},{"route_id":110,"route_long_name":"Islington South"},{"route_id":111,"route_long_name":"East Mall"},{"route_id":112,"route_long_name":"West Mall"},{"route_id":113,"route_long_name":"Danforth"},{"route_id":114,"route_long_name":"Queens Quay East"},{"route_id":115,"route_long_name":"Silver Hills"},{"route_id":116,"route_long_name":"Morningside"},{"route_id":117,"route_long_name":"Birchmount South"},{"route_id":118,"route_long_name":"Thistle Down"},{"route_id":119,"route_long_name":"Torbarrie"},{"route_id":120,"route_long_name":"Calvington"},{"route_id":121,"route_long_name":"Esplanade-River"},{"route_id":122,"route_long_name":"Graydon Hall"},{"route_id":123,"route_long_name":"Sherway"},{"route_id":124,"route_long_name":"Sunnybrook"},{"route_id":125,"route_long_name":"Drewry"},{"route_id":126,"route_long_name":"Christie"},{"route_id":127,"route_long_name":"Davenport"},{"route_id":129,"route_long_name":"McCowan North"},{"route_id":130,"route_long_name":"Middlefield"},{"route_id":131,"route_long_name":"Nugget"},{"route_id":132,"route_long_name":"Milner"},{"route_id":133,"route_long_name":"Neilson"},{"route_id":134,"route_long_name":"Progress"},{"route_id":135,"route_long_name":"Gerrard"},{"route_id":149,"route_long_name":"Etobicoke-Bloor"},{"route_id":154,"route_long_name":"Curran Hall"},{"route_id":158,"route_long_name":"Trethewey"},{"route_id":160,"route_long_name":"Bathurst North"},{"route_id":161,"route_long_name":"Rogers Rd"},{"route_id":162,"route_long_name":"Lawrence-Donway"},{"route_id":164,"route_long_name":"Castlefield"},{"route_id":165,"route_long_name":"Weston Rd North"},{"route_id":166,"route_long_name":"Toryork"},{"route_id":167,"route_long_name":"Pharmacy North"},{"route_id":168,"route_long_name":"Symington"},{"route_id":169,"route_long_name":"Huntingwood"},{"route_id":171,"route_long_name":"Mount Dennis"},{"route_id":184,"route_long_name":"Ancaster Park"},{"route_id":185,"route_long_name":"Sheppard Central"},{"route_id":189,"route_long_name":"Stockyards"},{"route_id":191,"route_long_name":"Underhill"},{"route_id":300,"route_long_name":"Bloor-Danforth"},{"route_id":301,"route_long_name":"Queen"},{"route_id":302,"route_long_name":"Kingston Rd-McCowan"},{"route_id":303,"route_long_name":"Kingston Rd"},{"route_id":304,"route_long_name":"King"},{"route_id":305,"route_long_name":"Dundas"},{"route_id":306,"route_long_name":"Carlton"},{"route_id":307,"route_long_name":"Bathurst"},{"route_id":310,"route_long_name":"Spadina"},{"route_id":312,"route_long_name":"St Clair"},{"route_id":315,"route_long_name":"Evans-Brown's Line"},{"route_id":320,"route_long_name":"Yonge"},{"route_id":322,"route_long_name":"Coxwell"},{"route_id":324,"route_long_name":"Victoria Park"},{"route_id":325,"route_long_name":"Don Mills"},{"route_id":329,"route_long_name":"Dufferin"},{"route_id":332,"route_long_name":"Eglinton West"},{"route_id":334,"route_long_name":"Eglinton East"},{"route_id":335,"route_long_name":"Jane"},{"route_id":336,"route_long_name":"Finch West"},{"route_id":337,"route_long_name":"Islington"},{"route_id":339,"route_long_name":"Finch East"},{"route_id":340,"route_long_name":"Junction"},{"route_id":341,"route_long_name":"Keele"},{"route_id":343,"route_long_name":"Kennedy"},{"route_id":352,"route_long_name":"Lawrence West"},{"route_id":353,"route_long_name":"Steeles"},{"route_id":354,"route_long_name":"Lawrence East"},{"route_id":363,"route_long_name":"Ossington"},{"route_id":365,"route_long_name":"Parliament"},{"route_id":384,"route_long_name":"Sheppard West"},{"route_id":385,"route_long_name":"Sheppard East"},{"route_id":386,"route_long_name":"Scarborough"},{"route_id":395,"route_long_name":"York Mills"},{"route_id":396,"route_long_name":"Wilson"},{"route_id":400,"route_long_name":"Lawrence Manor"},{"route_id":402,"route_long_name":"Parkdale"},{"route_id":403,"route_long_name":"South Don Mills"},{"route_id":404,"route_long_name":"East York"},{"route_id":405,"route_long_name":"Etobicoke"},{"route_id":406,"route_long_name":"Scarborough-Guildwood"},{"route_id":501,"route_long_name":"Queen"},{"route_id":503,"route_long_name":"Kingston Rd"},{"route_id":504,"route_long_name":"King"},{"route_id":505,"route_long_name":"Dundas"},{"route_id":506,"route_long_name":"Carlton"},{"route_id":507,"route_long_name":"Long Branch"},{"route_id":508,"route_long_name":"Lake Shore"},{"route_id":509,"route_long_name":"Harbourfront"},{"route_id":510,"route_long_name":"Spadina"},{"route_id":511,"route_long_name":"Bathurst"},{"route_id":512,"route_long_name":"St Clair"},{"route_id":806,"route_long_name":"Line 6 Shuttle"},{"route_id":882,"route_long_name":"Operator Shuttles"},{"route_id":900,"route_long_name":"Airport Express"},{"route_id":902,"route_long_name":"Markham Rd Express"},{"route_id":903,"route_long_name":"Kennedy Stn-Scarborough Express"},{"route_id":904,"route_long_name":"Sheppard-Kennedy Express"},{"route_id":905,"route_long_name":"Eglinton East Express"},{"route_id":924,"route_long_name":"Victoria Park Express"},{"route_id":925,"route_long_name":"Don Mills Express"},{"route_id":927,"route_long_name":"Highway 27 Express"},{"route_id":929,"route_long_name":"Dufferin Express"},{"route_id":935,"route_long_name":"Jane Express"},{"route_id":937,"route_long_name":"Islington Express"},{"route_id":938,"route_long_name":"Highland Creek Express"},{"route_id":939,"route_long_name":"Finch Express"},{"route_id":941,"route_long_name":"Keele Express"},{"route_id":944,"route_long_name":"Kipling South Express"},{"route_id":945,"route_long_name":"Kipling Express"},{"route_id":952,"route_long_name":"Lawrence West Express"},{"route_id":953,"route_long_name":"Steeles East Express"},{"route_id":954,"route_long_name":"Lawrence East Express"},{"route_id":960,"route_long_name":"Steeles West Express"},{"route_id":968,"route_long_name":"Warden Express"},{"route_id":984,"route_long_name":"Sheppard West Express"},{"route_id":985,"route_long_name":"Sheppard East Express"},{"route_id":986,"route_long_name":"Scarborough Express"},{"route_id":989,"route_long_name":"Weston Express"},{"route_id":995,"route_long_name":"York Mills Express"},{"route_id":996,"route_long_name":"Wilson Express"}]